lightningwatcher/__init__.py
lightning_watcher-0.0.1.dist-info/LICENSE
lightning_watcher-0.0.1.dist-info/METADATA
lightning_watcher-0.0.1.dist-info/WHEEL
lightning_watcher-0.0.1.dist-info/top_level.txt
lightning_watcher-0.0.1.dist-info/RECORD
